README.md
setup.cfg
setup.py
lologging/__init__.py
lologging/lologging.py
lologging.egg-info/PKG-INFO
lologging.egg-info/SOURCES.txt
lologging.egg-info/dependency_links.txt
lologging.egg-info/top_level.txt